MANIFEST.in
README.md
setup.cfg
setup.py
portproxy/__init__.py
portproxy/__main__.py
portproxy/forward.py
portproxy/portproxy.py
portproxy.egg-info/PKG-INFO
portproxy.egg-info/SOURCES.txt
portproxy.egg-info/dependency_links.txt
portproxy.egg-info/entry_points.txt
portproxy.egg-info/requires.txt
portproxy.egg-info/top_level.txt
portproxy/static/home.md
portproxy/static/style.css