Metadata-Version: 2.1
Name: portproxy
Version: 0.6.1
Summary: Automatically forward and manage ports from any remote machines.
Home-page: https://github.com/pseeth/portproxy/
Author: Prem Seetharaman
Author-email: prem@descript.com
License: UNKNOWN
Keywords: command-line configuration yaml argument parsing
Platform: UNKNOWN
Classifier: License :: OSI Approved :: MIT License
Classifier: Development Status :: 3 - Alpha
Classifier: Programming Language :: Python :: 3.6
Classifier: Programming Language :: Python :: 3.7
Classifier: Programming Language :: Python :: 3.8
Classifier: Operating System :: POSIX :: Linux
Classifier: Operating System :: MacOS
Classifier: Operating System :: Microsoft :: Windows
Requires-Python: >=3.5, <4
Provides-Extra: tests
